src/__init__.py
src/main.py
tests/__init__.py
tests/test_add.py
ernesto_pycicd-1.0.2.dist-info/METADATA
ernesto_pycicd-1.0.2.dist-info/WHEEL
ernesto_pycicd-1.0.2.dist-info/top_level.txt
ernesto_pycicd-1.0.2.dist-info/RECORD
