Metadata-Version: 2.4
Name: Ernesto_pycicd
Version: 1.0.2
Summary: Descripción de tu proyecto
Author: Ernesto Ruiz Hortelano
Author-email: coperinfofp@gmail.com
Requires-Dist: pytest
Requires-Dist: flake8
Dynamic: author
Dynamic: author-email
Dynamic: requires-dist
Dynamic: summary
